{
  "products": [
    {
      "key": 1,
      "properties": [
        { "label": "name", "value": "Iphone13" },
        { "label": "price", "value": 29990000 },
        { "label": "releaseDate", "value": "2023-09-12" },
        { "label": "brand", "value": "Apple" },
        { "label": "imageUrl", "value": "https://www.google.com/url?sa=i&url=https%3A%2F%2Fbluegiftvietnam.com%2Fqua-tang-noel-cho-khach-hang%2F&psig=AOvVaw0kSd6fRR3Gs_4CtMkYEP9S&ust=1767171911486000&source=images&cd=vfe&opi=89978449&ved=0CBIQjRxqFwoTCOCXycf65JEDFQAAAAAdAAAAABAK" }
      ]
    },
    {
      "key": 2,
      "properties": [
        { "label": "name", "value": "S23" },
        { "label": "price", "value": 25990000 },
        { "label": "releaseDate", "value": "2023-08-05" },
        { "label": "brand", "value": "Samsung" },
        { "label": "imageUrl", "value": "https://www.google.com/url?sa=i&url=https%3A%2F%2Fbluegiftvietnam.com%2Fqua-tang-noel-cho-khach-hang%2F&psig=AOvVaw0kSd6fRR3Gs_4CtMkYEP9S&ust=1767171911486000&source=images&cd=vfe&opi=89978449&ved=0CBIQjRxqFwoTCOCXycf65JEDFQAAAAAdAAAAABAK" }
      ]
    },
    {
      "key": 3,
      "properties": [
        { "label": "name", "value": "Iphone12" },
        { "label": "price", "value": 19990000 },
        { "label": "releaseDate", "value": "2023-07-20" },
        { "label": "brand", "value": "Apple" },
        { "label": "imageUrl", "value": "https://www.google.com/url?sa=i&url=https%3A%2F%2Fbluegiftvietnam.com%2Fqua-tang-noel-cho-khach-hang%2F&psig=AOvVaw0kSd6fRR3Gs_4CtMkYEP9S&ust=1767171911486000&source=images&cd=vfe&opi=89978449&ved=0CBIQjRxqFwoTCOCXycf65JEDFQAAAAAdAAAAABAK" }
      ]
    },
    {
      "key": 4,
      "properties": [
        { "label": "name", "value": "Iphone11" },
        { "label": "price", "value": 14990000 },
        { "label": "releaseDate", "value": "2023-06-15" },
        { "label": "brand", "value": "Apple" },
        { "label": "imageUrl", "value": "https://www.google.com/url?sa=i&url=https%3A%2F%2Fbluegiftvietnam.com%2Fqua-tang-noel-cho-khach-hang%2F&psig=AOvVaw0kSd6fRR3Gs_4CtMkYEP9S&ust=1767171911486000&source=images&cd=vfe&opi=89978449&ved=0CBIQjRxqFwoTCOCXycf65JEDFQAAAAAdAAAAABAK" }
      ]
    },
    {
      "key": 5,
      "properties": [
        { "label": "name", "value": "S24" },
        { "label": "price", "value": 12990000 },
        { "label": "releaseDate", "value": "2023-05-10" },
        { "label": "brand", "value": "Samsung" },
        { "label": "imageUrl", "value": "https://www.google.com/url?sa=i&url=https%3A%2F%2Fbluegiftvietnam.com%2Fqua-tang-noel-cho-khach-hang%2F&psig=AOvVaw0kSd6fRR3Gs_4CtMkYEP9S&ust=1767171911486000&source=images&cd=vfe&opi=89978449&ved=0CBIQjRxqFwoTCOCXycf65JEDFQAAAAAdAAAAABAK" }
      ]
    }
  ]
}
